scrapy_selenium_python_pi/__init__.py
scrapy_selenium_python_pi/http.py
scrapy_selenium_python_pi/middlewares.py
scrapy_selenium_python_pi-0.2.0.dist-info/DESCRIPTION.rst
scrapy_selenium_python_pi-0.2.0.dist-info/METADATA
scrapy_selenium_python_pi-0.2.0.dist-info/RECORD
scrapy_selenium_python_pi-0.2.0.dist-info/WHEEL
scrapy_selenium_python_pi-0.2.0.dist-info/metadata.json
scrapy_selenium_python_pi-0.2.0.dist-info/top_level.txt
tests/__init__.py
tests/test_cases.py
tests/test_middlewares.py
