Metadata-Version: 2.0
Name: scrapy-selenium-python-pi
Version: 0.2.0
Summary: Scrapy with selenium
Home-page: https://github.com/calincc/scrapy_selenium_python_pi
Author: UNKNOWN
Author-email: UNKNOWN
License: UNKNOWN
Platform: UNKNOWN
Requires-Dist: scrapy (>=1.0.0)
Requires-Dist: selenium (>=3.9.0)
